dir2chat.py
dir2chat-0.1.0a0.dist-info/licenses/LICENSE
dir2chat-0.1.0a0.dist-info/METADATA
dir2chat-0.1.0a0.dist-info/WHEEL
dir2chat-0.1.0a0.dist-info/top_level.txt
dir2chat-0.1.0a0.dist-info/RECORD
