Metadata-Version: 2.4
Name: dir2chat
Version: 0.1.0a0
Summary: Generate an OpenAI Chat Completions-compatible JSON from all UTF-8 plaintext files in a directory.
Author-email: Jifeng Wu <jifengwu2k@gmail.com>
License-Expression: MIT
Project-URL: Homepage, https://github.com/jifengwu2k/dir2chat
Project-URL: Bug Tracker, https://github.com/jifengwu2k/dir2chat/issues
Classifier: Programming Language :: Python :: 2
Classifier: Programming Language :: Python :: 3
Classifier: Operating System :: OS Independent
Requires-Python: >=2
License-File: LICENSE
Requires-Dist: build-filesystem-trie
Requires-Dist: cowlist
Requires-Dist: tinytrie
Requires-Dist: typing; python_version < "3.5"
Dynamic: license-file
